[
  {
    "constant": true,
    "inputs": [
      {
        "name": "addr",
        "type": "address"
      },
      {
        "name": "roleName",
        "type": "string"
      }
    ],
    "name": "checkRole",
    "outputs": [],
    "payable": false,
    "stateMutability": "view",
    "type": "function"
  },
  {
    "constant": true,
    "inputs": [
      {
        "name": "addr",
        "type": "address"
      },
      {
        "name": "roleName",
        "type": "string"
      }
    ],
    "name": "hasRole",
    "outputs": [
      {
        "name": "",
        "type": "bool"
      }
    ],
    "payable": false,
    "stateMutability": "view",
    "type": "function"
  },
  {
    "constant": true,
    "inputs": [],
    "name": "ROLE_AUDIT_UPDATER",
    "outputs": [
      {
        "name": "",
        "type": "string"
      }
    ],
    "payable": false,
    "stateMutability": "view",
    "type": "function"
  },
  {
    "constant": true,
    "inputs": [],
    "name": "auditUpdater",
    "outputs": [
      {
        "name": "",
        "type": "address"
      }
    ],
    "payable": false,
    "stateMutability": "view",
    "type": "function"
  },
  {
    "constant": true,
    "inputs": [],
    "name": "owner",
    "outputs": [
      {
        "name": "",
        "type": "address"
      }
    ],
    "payable": false,
    "stateMutability": "view",
    "type": "function"
  },
  {
    "anonymous": false,
    "inputs": [
      {
        "indexed": true,
        "name": "eventType",
        "type": "bytes20"
      },
      {
        "indexed": false,
        "name": "eventRawString",
        "type": "string"
      },
      {
        "indexed": false,
        "name": "contentHash",
        "type": "bytes20"
      }
    ],
    "name": "AuditableEventCreated",
    "type": "event"
  },
  {
    "anonymous": false,
    "inputs": [
      {
        "indexed": false,
        "name": "addr",
        "type": "address"
      },
      {
        "indexed": false,
        "name": "roleName",
        "type": "string"
      }
    ],
    "name": "RoleAdded",
    "type": "event"
  },
  {
    "anonymous": false,
    "inputs": [
      {
        "indexed": false,
        "name": "addr",
        "type": "address"
      },
      {
        "indexed": false,
        "name": "roleName",
        "type": "string"
      }
    ],
    "name": "RoleRemoved",
    "type": "event"
  },
  {
    "constant": false,
    "inputs": [
      {
        "name": "addr",
        "type": "address"
      }
    ],
    "name": "addAuditUpdater",
    "outputs": [],
    "payable": false,
    "stateMutability": "nonpayable",
    "type": "function"
  },
  {
    "constant": false,
    "inputs": [
      {
        "name": "addr",
        "type": "address"
      }
    ],
    "name": "removeAuditUpdater",
    "outputs": [],
    "payable": false,
    "stateMutability": "nonpayable",
    "type": "function"
  },
  {
    "constant": false,
    "inputs": [
      {
        "name": "eventTypeHash",
        "type": "bytes20"
      },
      {
        "name": "eventType",
        "type": "string"
      },
      {
        "name": "contentHash",
        "type": "bytes20"
      }
    ],
    "name": "createAuditableEvent",
    "outputs": [],
    "payable": false,
    "stateMutability": "nonpayable",
    "type": "function"
  }
]
